{"cuit":"934058","responsabilidad":"Responsable Inscripto","razonSocial":"Traslados del Sol SRL","nombre":"Traslados del Sol","direccion":"Callao 9684","telefono":"9745654203","mail":"delSol@algo.com","ingresosBrutos":1569999,"fechaInicioActividades":"1980-03-03","productoPorProvedor":[{"idProductoPorProveedor":1,"ultimoPrecio":5500,"producto":{"idProducto":1,"nombreProducto":"Traslado menos 15km","rubro":"VIATICOS_MOVILIDAD","tipoUnidad":"UNIDAD","tipoIva":0.105}},{"idProductoPorProveedor":3,"ultimoPrecio":10500,"producto":{"idProducto":2,"nombreProducto":"Traslado mas 15km","rubro":"VIATICOS_MOVILIDAD","tipoUnidad":"UNIDAD","tipoIva":0.05}}]}
{"cuit":"2459888","responsabilidad":"Responsable Inscripto","razonSocial":"Traslados Lunita S.A","nombre":"Traslados Lunita","direccion":"Corrientes 684","telefono":"115987845","mail":"lunita@algo.com","ingresosBrutos":9999,"fechaInicioActividades":"1997-08-03","productoPorProvedor":[{"idProductoPorProveedor":2,"ultimoPrecio":4500,"producto":{"idProducto":1,"nombreProducto":"Traslado menos 15km","rubro":"VIATICOS_MOVILIDAD","tipoUnidad":"UNIDAD","tipoIva":0.105}},{"idProductoPorProveedor":4,"ultimoPrecio":8500,"producto":{"idProducto":2,"nombreProducto":"Traslado mas 15km","rubro":"VIATICOS_MOVILIDAD","tipoUnidad":"UNIDAD","tipoIva":0.05}}]}
{"cuit":"002255777111400","responsabilidad":"Responsable Inscripto","razonSocial":"Muebleria Buenos Aires SRL","nombre":"Muebleria Buenos Aires","direccion":"Buenos Aires 1234","telefono":"1235345653","mail":"muebleria_ba@algo.com","ingresosBrutos":8887710,"fechaInicioActividades":"2020-02-20","productoPorProvedor":[{"idProductoPorProveedor":5,"ultimoPrecio":4500,"producto":{"idProducto":3,"nombreProducto":"Reparacion mueble madera chico","rubro":"MANTENIMINETO_MUEBLES","tipoUnidad":"UNIDAD","tipoIva":0.27}},{"idProductoPorProveedor":7,"ultimoPrecio":6500,"producto":{"idProducto":4,"nombreProducto":"Reparacion mueble madera mediano","rubro":"MANTENIMINETO_MUEBLES","tipoUnidad":"UNIDAD","tipoIva":0.21}}]}
{"cuit":"697874","responsabilidad":"Responsable Inscripto","razonSocial":"Muebles bonitos SRL","nombre":"Muebles bonitos","direccion":"Alberdi 1234","telefono":"115987411","mail":"bonitos@algo.com","ingresosBrutos":88971000,"fechaInicioActividades":"2010-09-25","productoPorProvedor":[{"idProductoPorProveedor":6,"ultimoPrecio":7500,"producto":{"idProducto":3,"nombreProducto":"Reparacion mueble madera chico","rubro":"MANTENIMINETO_MUEBLES","tipoUnidad":"UNIDAD","tipoIva":0.27}},{"idProductoPorProveedor":8,"ultimoPrecio":6000,"producto":{"idProducto":4,"nombreProducto":"Reparacion mueble madera mediano","rubro":"MANTENIMINETO_MUEBLES","tipoUnidad":"UNIDAD","tipoIva":0.21}}]}
{"cuit":"35521","responsabilidad":"Responsable Inscripto","razonSocial":"Papelera Martinez SA","nombre":"Papelera Martinez","direccion":"Av Cordoba 490","telefono":"36884651626","mail":"papelmar@algo.com","ingresosBrutos":569000,"fechaInicioActividades":"1999-05-06","productoPorProvedor":[{"idProductoPorProveedor":9,"ultimoPrecio":1000,"producto":{"idProducto":5,"nombreProducto":"Vasos descartables","rubro":"PAPELERIA_IMPRESIONES","tipoUnidad":"UNIDAD","tipoIva":0.105}},{"idProductoPorProveedor":11,"ultimoPrecio":7100,"producto":{"idProducto":6,"nombreProducto":"Cajas papel","rubro":"PAPELERIA_IMPRESIONES","tipoUnidad":"UNIDAD","tipoIva":0.27}}]}
{"cuit":"58744","responsabilidad":"Responsable Inscripto","razonSocial":"Papelito SA","nombre":"Papelito","direccion":"Av Corrientes 490","telefono":"368844777","mail":"papelito@algo.com","ingresosBrutos":560,"fechaInicioActividades":"1919-01-06","productoPorProvedor":[{"idProductoPorProveedor":10,"ultimoPrecio":4000,"producto":{"idProducto":5,"nombreProducto":"Vasos descartables","rubro":"PAPELERIA_IMPRESIONES","tipoUnidad":"UNIDAD","tipoIva":0.105}},{"idProductoPorProveedor":12,"ultimoPrecio":5500,"producto":{"idProducto":6,"nombreProducto":"Cajas papel","rubro":"PAPELERIA_IMPRESIONES","tipoUnidad":"UNIDAD","tipoIva":0.27}}]}
{"cuit":"23547444448","responsabilidad":"Responsable Inscripto","razonSocial":"Farmacia Luna S.A","nombre":"Farmacia Luna","direccion":"Av. Corrientes 1234","telefono":"1235345653","mail":"farmacialuna@hotmail.com","ingresosBrutos":5000,"fechaInicioActividades":"2020-02-28","productoPorProvedor":[{"idProductoPorProveedor":13,"ultimoPrecio":1000,"producto":{"idProducto":7,"nombreProducto":"Paracetamol","rubro":"MEDICINA_PREPAGA","tipoUnidad":"UNIDAD","tipoIva":0.025}},{"idProductoPorProveedor":15,"ultimoPrecio":3500,"producto":{"idProducto":8,"nombreProducto":"Ibuprofeno","rubro":"MEDICINA_PREPAGA","tipoUnidad":"UNIDAD","tipoIva":0.025}}]}
{"cuit":"11111147","responsabilidad":"Responsable Inscripto","razonSocial":"Farmaciudad S.R.L","nombre":"Farmaciudad","direccion":"Av. Flores 1234","telefono":"115799987","mail":"farmaciudad@hotmail.com","ingresosBrutos":5100000,"fechaInicioActividades":"2000-07-28","productoPorProvedor":[{"idProductoPorProveedor":14,"ultimoPrecio":1500,"producto":{"idProducto":7,"nombreProducto":"Paracetamol","rubro":"MEDICINA_PREPAGA","tipoUnidad":"UNIDAD","tipoIva":0.025}},{"idProductoPorProveedor":16,"ultimoPrecio":3800,"producto":{"idProducto":8,"nombreProducto":"Ibuprofeno","rubro":"MEDICINA_PREPAGA","tipoUnidad":"UNIDAD","tipoIva":0.025}}]}
{"cuit":"9666747187818","responsabilidad":"Responsable Inscripto","razonSocial":"Segunda Mano SRL","nombre":"Segunda Mano","direccion":"Buenos Aires 1234","telefono":"1235345653","mail":"segundamano@yahoo.com","ingresosBrutos":5000,"fechaInicioActividades":"2020-02-20","productoPorProvedor":[{"idProductoPorProveedor":17,"ultimoPrecio":50000,"producto":{"idProducto":9,"nombreProducto":"Televisor 32 pulgadas","rubro":"PRODUCTOS_REVENTA","tipoUnidad":"UNIDAD","tipoIva":0.21}},{"idProductoPorProveedor":19,"ultimoPrecio":100000,"producto":{"idProducto":10,"nombreProducto":"Televisor 42 pulgadas","rubro":"PRODUCTOS_REVENTA","tipoUnidad":"UNIDAD","tipoIva":0.21}}]}
{"cuit":"99914570","responsabilidad":"Responsable Inscripto","razonSocial":"Libre mercado SRL","nombre":"Libre mercado","direccion":"soledad  1234","telefono":"1235343","mail":"libremercado@yahoo.com","ingresosBrutos":11111110,"fechaInicioActividades":"2023-02-20","productoPorProvedor":[{"idProductoPorProveedor":18,"ultimoPrecio":59000,"producto":{"idProducto":9,"nombreProducto":"Televisor 32 pulgadas","rubro":"PRODUCTOS_REVENTA","tipoUnidad":"UNIDAD","tipoIva":0.21}},{"idProductoPorProveedor":20,"ultimoPrecio":120000,"producto":{"idProducto":10,"nombreProducto":"Televisor 42 pulgadas","rubro":"PRODUCTOS_REVENTA","tipoUnidad":"UNIDAD","tipoIva":0.21}}]}
{"cuit":"115777880456","responsabilidad":"Responsable Inscripto","razonSocial":"Libreria de Jose SRL","nombre":"Libreria de Jose","direccion":"Rivadavia 555","telefono":"115698722","mail":"josefernandez@gmail.com","ingresosBrutos":10000,"fechaInicioActividades":"2007-07-21","productoPorProvedor":[{"idProductoPorProveedor":21,"ultimoPrecio":5000,"producto":{"idProducto":11,"nombreProducto":"Cuadernillos universitarios","rubro":"LIBRERIA","tipoUnidad":"UNIDAD","tipoIva":0.21}},{"idProductoPorProveedor":23,"ultimoPrecio":10000,"producto":{"idProducto":12,"nombreProducto":"Cuadernillos escolares","rubro":"LIBRERIA","tipoUnidad":"UNIDAD","tipoIva":0.21}}]}
{"cuit":"1047004900","responsabilidad":"Responsable Inscripto","razonSocial":"Libreria de RAUL SA","nombre":"Libreria de RAUL","direccion":"Rivadavia 553","telefono":"1156984472","mail":"RAULITO@gmail.com","ingresosBrutos":100001141474,"fechaInicioActividades":"2007-07-21","productoPorProvedor":[{"idProductoPorProveedor":22,"ultimoPrecio":6000,"producto":{"idProducto":11,"nombreProducto":"Cuadernillos universitarios","rubro":"LIBRERIA","tipoUnidad":"UNIDAD","tipoIva":0.21}},{"idProductoPorProveedor":24,"ultimoPrecio":8000,"producto":{"idProducto":12,"nombreProducto":"Cuadernillos escolares","rubro":"LIBRERIA","tipoUnidad":"UNIDAD","tipoIva":0.21}}]}]